ClassiPyGRB/__init__.py
ClassiPyGRB/_swift.py
ClassiPyGRB/_tools.py
ClassiPyGRB/_viewer.py
ClassiPyGRB/__pycache__/__init__.cpython-310.pyc
ClassiPyGRB/__pycache__/_swift.cpython-310.pyc
ClassiPyGRB/__pycache__/_tools.cpython-310.pyc
ClassiPyGRB/__pycache__/_viewer.cpython-310.pyc
ClassiPyGRB/summary_tables/GRBlist_redshift_BAT.txt
ClassiPyGRB/summary_tables/summary_burst_durations.txt
ClassiPyGRB/summary_tables/summary_general.txt
ClassiPyGRB-1.0.0.dist-info/LICENSE
ClassiPyGRB-1.0.0.dist-info/METADATA
ClassiPyGRB-1.0.0.dist-info/WHEEL
ClassiPyGRB-1.0.0.dist-info/top_level.txt
ClassiPyGRB-1.0.0.dist-info/RECORD
