Metadata-Version: 2.1
Name: ClassiPyGRB
Version: 1.0.0
Summary: Download, process, visualize and classify Gamma-Ray-Bursts (GRB) from the Swift/BAT Telescope database.
Author-email: "Garcia-Cifuentes, K." <keneth.garcia@correo.nucleares.unam.mx>, "Becerra, R. L." <rosa.becerra@correo.nucleares.unam.mx>, "De Colle, F." <fabio@nucleares.unam.mx>
Maintainer-email: Keneth Garcia <keneth.garcia@correo.nucleares.unam.mx>
License: GNU GENERAL PUBLIC LICENSE
Project-URL: homepage, https://github.com/KenethGarcia/ClassiPyGRB
Project-URL: documentation, https://github.com/KenethGarcia/ClassiPyGRB/tree/master/docs
Keywords: Swift,BAT,Gamma-Ray-Burst,Swift/BAT,TSNE,Transients,Extragalactic Astronomy
Classifier: Development Status :: 5 - Production/Stable
Classifier: Intended Audience :: Education
Classifier: Intended Audience :: Information Technology
Classifier: Intended Audience :: Science/Research
Classifier: Topic :: Scientific/Engineering :: Artificial Intelligence
Classifier: Topic :: Scientific/Engineering :: Astronomy
Classifier: Topic :: Software Development :: Libraries :: Python Modules
Classifier: License :: OSI Approved :: GNU General Public License v2 (GPLv2)
Classifier: Programming Language :: Python :: 3.8
Classifier: Programming Language :: Python :: 3.9
Classifier: Programming Language :: Python :: 3.10
Classifier: Programming Language :: Python :: Implementation
Classifier: Natural Language :: English
Classifier: Operating System :: Microsoft :: Windows
Classifier: Operating System :: POSIX :: Linux
Requires-Python: >=3.8
License-File: LICENSE
Requires-Dist: fabada (==0.1)
Requires-Dist: matplotlib (==3.7.1)
Requires-Dist: moviepy (==1.0.3)
Requires-Dist: numpy (==1.24.2)
Requires-Dist: openTSNE (==0.7.1)
Requires-Dist: pandas (==2.0.0)
Requires-Dist: requests (==2.29.0)
Requires-Dist: scikit-learn (==1.2.2)
Requires-Dist: scipy (==1.10.1)
Requires-Dist: tqdm (==4.65.0)
Requires-Dist: tables (==3.8.0)
